smpConsole/__init__.py
smpConsole/console.py
smpconsole-1.0.2.dist-info/METADATA
smpconsole-1.0.2.dist-info/WHEEL
smpconsole-1.0.2.dist-info/top_level.txt
smpconsole-1.0.2.dist-info/RECORD
