Metadata-Version: 2.1
Name: smpconsole
Version: 1.0.2
Summary: best console experience
Home-page: https://github.com/khimnguynnn/smpConsole
Author: khiemndd
Classifier: Programming Language :: Python :: 3
Classifier: License :: OSI Approved :: MIT License
Classifier: Operating System :: OS Independent
Requires-Python: >=3.0
Requires-Dist: colorama
